gthb/__init__.py
gthb/gthb.py
gthb-0.0.1.dist-info/LICENSE
gthb-0.0.1.dist-info/METADATA
gthb-0.0.1.dist-info/WHEEL
gthb-0.0.1.dist-info/top_level.txt
gthb-0.0.1.dist-info/RECORD
